chi_edge/__init__.py
chi_edge/__main__.py
chi_edge/cli.py
chi_edge/image.py
chi_edge/utils.py
chi_edge/vendor/FATtools/FAT.py
chi_edge/vendor/FATtools/README.MD
chi_edge/vendor/FATtools/Volume.py
chi_edge/vendor/FATtools/__init__.py
chi_edge/vendor/FATtools/cp.py
chi_edge/vendor/FATtools/crc32c.py
chi_edge/vendor/FATtools/debug.py
chi_edge/vendor/FATtools/disk.py
chi_edge/vendor/FATtools/exFAT.py
chi_edge/vendor/FATtools/gpl.txt
chi_edge/vendor/FATtools/gptutils.py
chi_edge/vendor/FATtools/mkvdisk.py
chi_edge/vendor/FATtools/partutils.py
chi_edge/vendor/FATtools/utils.py
chi_edge/vendor/FATtools/vdiutils.py
chi_edge/vendor/FATtools/vhdutils.py
chi_edge/vendor/FATtools/vhdxlog.py
chi_edge/vendor/FATtools/vhdxutils.py
chi_edge/vendor/FATtools/vmdkutils.py
chi_edge/vendor/FATtools/win32enumvols.py
python_chi_edge-0.2.4.dist-info/LICENSE
python_chi_edge-0.2.4.dist-info/METADATA
python_chi_edge-0.2.4.dist-info/WHEEL
python_chi_edge-0.2.4.dist-info/entry_points.txt
python_chi_edge-0.2.4.dist-info/RECORD
