Metadata-Version: 2.3
Name: python-chi-edge
Version: 0.2.4
Summary: Manage edge devices for use with the CHI@Edge IoT/Edge testbed.
Author: Chameleon Project
Author-email: contact@chameleoncloud.org
Requires-Python: >=3.6.2,<4.0.0
Classifier: Programming Language :: Python :: 3
Classifier: Programming Language :: Python :: 3.7
Classifier: Programming Language :: Python :: 3.8
Classifier: Programming Language :: Python :: 3.9
Classifier: Programming Language :: Python :: 3.10
Classifier: Programming Language :: Python :: 3.11
Classifier: Programming Language :: Python :: 3.12
Classifier: Programming Language :: Python :: 3.13
Requires-Dist: PyYAML (>=6.0,<7.0)
Requires-Dist: click (>=8.0.1,<9.0.0)
Requires-Dist: keystoneauth1 (>=4.4.0,<5.0.0)
Requires-Dist: python-chi (>=0.15.4,<0.16.0)
Requires-Dist: rich (>=11.2.0,<12.0.0)
